aftr/__init__.py
aftr/cli.py
aftr/commands/__init__.py
aftr/commands/init.py
aftr-0.1.1.dist-info/METADATA
aftr-0.1.1.dist-info/WHEEL
aftr-0.1.1.dist-info/entry_points.txt
aftr-0.1.1.dist-info/RECORD
