Metadata-Version: 2.4
Name: aftr
Version: 0.1.1
Summary: CLI for bootstrapping Python data projects with UV, mise, and papermill
Requires-Python: >=3.11
Requires-Dist: inquirerpy>=0.3.4
Requires-Dist: rich>=13.0.0
Requires-Dist: typer>=0.9.0
